<?xml version="1.0" encoding="UTF-8"?>
<cmamDocument xmlns="http://www.cen.bris.ac.uk/civil/cmam" xmlns:xsi="http://www.w3.org/2001/XMLSchema-instance" xsi:schemaLocation="http://www.cen.bris.ac.uk/civil/cmam cmam-model.xsd" editedInVersion="2.1.7Beta">
  <model name="WS1_G1" learningRate="1.0" necessityPower="1.0" propagationAlgorithm="Belief Propagation" normalizationMethod="Yager's Method" pairwiseCombinationMethod="Minimum of pairs" />
  <aspect id="0" name="Overview" colour="-1" />
  <process>
    <node id="1" name="Obtaining Base Live Data on Stats">
      <location x="555" y="125" nodeWidth="84" nodeHeight="80" />
      <colour>-2302756</colour>
      <nodeAspect aspectId="0">
        <localFOM>
          <sn>0.51</sn>
          <sp>1.0</sp>
        </localFOM>
        <propFOM>
          <noEvidence />
        </propFOM>
        <localFOMWeight>1.0</localFOMWeight>
        <propFOMWeight>1.0</propFOMWeight>
        <localFOMDirect>true</localFOMDirect>
        <dependancy>
          <single>0.0</single>
        </dependancy>
      </nodeAspect>
    </node>
  </process>
  <process>
    <node id="2" name="Establishing the Infrastructure Planning ">
      <location x="390" y="10" nodeWidth="84" nodeHeight="80" />
      <colour>-2302756</colour>
      <graphExpanded>true</graphExpanded>
      <nodeAspect aspectId="0">
        <localFOM>
          <noEvidence />
        </localFOM>
        <propFOM>
          <sn>0.49328237</sn>
          <sp>0.49417105</sp>
        </propFOM>
        <localFOMWeight>1.0</localFOMWeight>
        <propFOMWeight>1.0</propFOMWeight>
        <localFOMDirect>false</localFOMDirect>
        <dependancy>
          <single>0.0</single>
        </dependancy>
      </nodeAspect>
    </node>
  </process>
  <process>
    <node id="3" name="Investigating the Delivery Method">
      <location x="350" y="125" nodeWidth="84" nodeHeight="80" />
      <colour>-2302756</colour>
      <graphExpanded>true</graphExpanded>
      <nodeAspect aspectId="0">
        <localFOM>
          <sn>0.56</sn>
          <sp>1.0</sp>
        </localFOM>
        <propFOM>
          <sn>0.48151072</sn>
          <sp>0.48350119</sp>
        </propFOM>
        <localFOMWeight>1.0</localFOMWeight>
        <propFOMWeight>1.0</propFOMWeight>
        <localFOMDirect>true</localFOMDirect>
        <dependancy>
          <single>0.0</single>
        </dependancy>
      </nodeAspect>
    </node>
  </process>
  <process>
    <node id="4" name="Knowing Demand">
      <location x="455" y="125" nodeWidth="84" nodeHeight="80" />
      <colour>-2302756</colour>
      <graphExpanded>true</graphExpanded>
      <nodeAspect aspectId="0">
        <localFOM>
          <sn>0.315</sn>
          <sp>0.61</sp>
        </localFOM>
        <propFOM>
          <sn>0.53600703</sn>
          <sp>0.56487971</sp>
        </propFOM>
        <localFOMWeight>1.0</localFOMWeight>
        <propFOMWeight>1.0</propFOMWeight>
        <localFOMDirect>true</localFOMDirect>
        <dependancy>
          <single>0.0</single>
        </dependancy>
      </nodeAspect>
    </node>
  </process>
  <process>
    <node id="5" name="Define Infrastructure">
      <location x="220" y="125" nodeWidth="84" nodeHeight="80" />
      <colour>-2302756</colour>
      <graphExpanded>true</graphExpanded>
      <nodeAspect aspectId="0">
        <localFOM>
          <sn>0.97</sn>
          <sp>0.98</sp>
        </localFOM>
        <propFOM>
          <sn>0.5194</sn>
          <sp>0.7516</sp>
        </propFOM>
        <localFOMWeight>1.0</localFOMWeight>
        <propFOMWeight>1.0</propFOMWeight>
        <localFOMDirect>true</localFOMDirect>
        <dependancy>
          <single>0.0</single>
        </dependancy>
      </nodeAspect>
    </node>
  </process>
  <process>
    <node id="6" name="Identifying User Type">
      <location x="370" y="305" nodeWidth="84" nodeHeight="80" />
      <colour>-2302756</colour>
      <graphExpanded>true</graphExpanded>
      <nodeAspect aspectId="0">
        <localFOM>
          <sn>0.01</sn>
          <sp>0.255</sp>
        </localFOM>
        <propFOM>
          <sn>0.71627529</sn>
          <sp>0.72730298</sp>
        </propFOM>
        <localFOMWeight>1.0</localFOMWeight>
        <propFOMWeight>1.0</propFOMWeight>
        <localFOMDirect>true</localFOMDirect>
        <dependancy>
          <single>0.0</single>
        </dependancy>
      </nodeAspect>
    </node>
  </process>
  <process>
    <node id="7" name="Reviewing Market INterest">
      <location x="405" y="410" nodeWidth="84" nodeHeight="80" />
      <colour>-2302756</colour>
      <nodeAspect aspectId="0">
        <localFOM>
          <noEvidence />
        </localFOM>
        <propFOM>
          <noEvidence />
        </propFOM>
        <localFOMWeight>1.0</localFOMWeight>
        <propFOMWeight>1.0</propFOMWeight>
        <localFOMDirect>false</localFOMDirect>
        <dependancy>
          <single>0.0</single>
        </dependancy>
      </nodeAspect>
    </node>
  </process>
  <process>
    <node id="8" name="Reviewiung of existing Buildings ">
      <location x="510" y="310" nodeWidth="84" nodeHeight="80" />
      <colour>-2302756</colour>
      <nodeAspect aspectId="0">
        <localFOM>
          <sn>0.49</sn>
          <sp>1.0</sp>
        </localFOM>
        <propFOM>
          <noEvidence />
        </propFOM>
        <localFOMWeight>1.0</localFOMWeight>
        <propFOMWeight>1.0</propFOMWeight>
        <localFOMDirect>true</localFOMDirect>
        <dependancy>
          <single>0.0</single>
        </dependancy>
      </nodeAspect>
    </node>
  </process>
  <process>
    <node id="9" name="Setting tenant specificantion s/ user type">
      <location x="510" y="410" nodeWidth="84" nodeHeight="80" />
      <colour>-2302756</colour>
      <nodeAspect aspectId="0">
        <localFOM>
          <sn>0.0</sn>
          <sp>0.03</sp>
        </localFOM>
        <propFOM>
          <noEvidence />
        </propFOM>
        <localFOMWeight>1.0</localFOMWeight>
        <propFOMWeight>1.0</propFOMWeight>
        <localFOMDirect>true</localFOMDirect>
        <dependancy>
          <single>0.0</single>
        </dependancy>
      </nodeAspect>
    </node>
  </process>
  <process>
    <node id="10" name="Public/ Private Sector Partnership ">
      <location x="207" y="301" nodeWidth="84" nodeHeight="80" />
      <colour>-2302756</colour>
      <graphExpanded>true</graphExpanded>
      <nodeAspect aspectId="0">
        <localFOM>
          <noEvidence />
        </localFOM>
        <propFOM>
          <sn>0.72313713</sn>
          <sp>0.72682318</sp>
        </propFOM>
        <localFOMWeight>1.0</localFOMWeight>
        <propFOMWeight>1.0</propFOMWeight>
        <localFOMDirect>false</localFOMDirect>
        <dependancy>
          <single>0.0</single>
        </dependancy>
      </nodeAspect>
    </node>
  </process>
  <process>
    <node id="11" name="Funding">
      <location x="187" y="482" nodeWidth="84" nodeHeight="80" />
      <colour>-2302756</colour>
      <nodeAspect aspectId="0">
        <localFOM>
          <noEvidence />
        </localFOM>
        <propFOM>
          <noEvidence />
        </propFOM>
        <localFOMWeight>1.0</localFOMWeight>
        <propFOMWeight>1.0</propFOMWeight>
        <localFOMDirect>false</localFOMDirect>
        <dependancy>
          <single>0.0</single>
        </dependancy>
      </nodeAspect>
    </node>
  </process>
  <process>
    <node id="12" name="Encourage Use of Infrastructure">
      <location x="30" y="420" nodeWidth="84" nodeHeight="80" />
      <colour>-2302756</colour>
      <nodeAspect aspectId="0">
        <localFOM>
          <sn>0.0</sn>
          <sp>0.01</sp>
        </localFOM>
        <propFOM>
          <noEvidence />
        </propFOM>
        <localFOMWeight>1.0</localFOMWeight>
        <propFOMWeight>1.0</propFOMWeight>
        <localFOMDirect>true</localFOMDirect>
        <dependancy>
          <single>0.0</single>
        </dependancy>
      </nodeAspect>
    </node>
  </process>
  <process>
    <node id="13" name="(Supply) Local Energy Generation">
      <location x="70" y="225" nodeWidth="84" nodeHeight="80" />
      <desc>Zero Waste
100% Renewables</desc>
      <colour>-2302756</colour>
      <nodeAspect aspectId="0">
        <localFOM>
          <sn>0.0</sn>
          <sp>0.43</sp>
        </localFOM>
        <propFOM>
          <noEvidence />
        </propFOM>
        <localFOMWeight>1.0</localFOMWeight>
        <propFOMWeight>1.0</propFOMWeight>
        <localFOMDirect>true</localFOMDirect>
        <dependancy>
          <single>0.0</single>
        </dependancy>
      </nodeAspect>
    </node>
  </process>
  <link parentNodeId="2" childNodeId="4">
    <linkAspect aspectId="0">
      <necessity>0.3</necessity>
      <sufficiency>0.4</sufficiency>
      <importance>1.0</importance>
      <jointlySufficient>false</jointlySufficient>
      <jointlyNecessary>false</jointlyNecessary>
    </linkAspect>
  </link>
  <link parentNodeId="2" childNodeId="5">
    <linkAspect aspectId="0">
      <necessity>0.3</necessity>
      <sufficiency>0.4</sufficiency>
      <importance>1.0</importance>
      <jointlySufficient>false</jointlySufficient>
      <jointlyNecessary>false</jointlyNecessary>
    </linkAspect>
  </link>
  <link parentNodeId="6" childNodeId="7">
    <linkAspect aspectId="0">
      <necessity>0.3</necessity>
      <sufficiency>0.4</sufficiency>
      <importance>1.0</importance>
      <jointlySufficient>false</jointlySufficient>
      <jointlyNecessary>false</jointlyNecessary>
    </linkAspect>
  </link>
  <link parentNodeId="4" childNodeId="6">
    <linkAspect aspectId="0">
      <necessity>0.3</necessity>
      <sufficiency>0.4</sufficiency>
      <importance>1.0</importance>
      <jointlySufficient>false</jointlySufficient>
      <jointlyNecessary>false</jointlyNecessary>
    </linkAspect>
  </link>
  <link parentNodeId="4" childNodeId="8">
    <linkAspect aspectId="0">
      <necessity>0.3</necessity>
      <sufficiency>0.4</sufficiency>
      <importance>1.0</importance>
      <jointlySufficient>false</jointlySufficient>
      <jointlyNecessary>false</jointlyNecessary>
    </linkAspect>
  </link>
  <link parentNodeId="6" childNodeId="9">
    <linkAspect aspectId="0">
      <necessity>0.3</necessity>
      <sufficiency>0.4</sufficiency>
      <importance>1.0</importance>
      <jointlySufficient>false</jointlySufficient>
      <jointlyNecessary>false</jointlyNecessary>
    </linkAspect>
  </link>
  <link parentNodeId="2" childNodeId="1">
    <linkAspect aspectId="0">
      <necessity>0.3</necessity>
      <sufficiency>0.4</sufficiency>
      <importance>1.0</importance>
      <jointlySufficient>false</jointlySufficient>
      <jointlyNecessary>false</jointlyNecessary>
    </linkAspect>
  </link>
  <link parentNodeId="2" childNodeId="3">
    <linkAspect aspectId="0">
      <necessity>0.3</necessity>
      <sufficiency>0.4</sufficiency>
      <importance>1.0</importance>
      <jointlySufficient>false</jointlySufficient>
      <jointlyNecessary>false</jointlyNecessary>
    </linkAspect>
  </link>
  <link parentNodeId="3" childNodeId="10">
    <linkAspect aspectId="0">
      <necessity>0.3</necessity>
      <sufficiency>0.4</sufficiency>
      <importance>1.0</importance>
      <jointlySufficient>false</jointlySufficient>
      <jointlyNecessary>false</jointlyNecessary>
    </linkAspect>
  </link>
  <link parentNodeId="10" childNodeId="11">
    <linkAspect aspectId="0">
      <necessity>0.3</necessity>
      <sufficiency>0.4</sufficiency>
      <importance>1.0</importance>
      <jointlySufficient>false</jointlySufficient>
      <jointlyNecessary>false</jointlyNecessary>
    </linkAspect>
  </link>
  <link parentNodeId="10" childNodeId="12">
    <linkAspect aspectId="0">
      <necessity>0.3</necessity>
      <sufficiency>0.4</sufficiency>
      <importance>1.0</importance>
      <jointlySufficient>false</jointlySufficient>
      <jointlyNecessary>false</jointlyNecessary>
    </linkAspect>
  </link>
  <link parentNodeId="5" childNodeId="13">
    <linkAspect aspectId="0">
      <necessity>0.3</necessity>
      <sufficiency>0.4</sufficiency>
      <importance>1.0</importance>
      <jointlySufficient>false</jointlySufficient>
      <jointlyNecessary>false</jointlyNecessary>
    </linkAspect>
  </link>
</cmamDocument>

